crystal/Crystal.py
crystal/__init__.py
crystal/app.py
crystal/sql_table_utils.py
crystal/static/css/crystal_dashboard_stylesheet.css
crystal/static/fonts/roboto/Roboto-Bold.woff
crystal/static/fonts/roboto/Roboto-Bold.woff2
crystal/static/fonts/roboto/Roboto-Light.woff
crystal/static/fonts/roboto/Roboto-Light.woff2
crystal/static/fonts/roboto/Roboto-Medium.woff
crystal/static/fonts/roboto/Roboto-Medium.woff2
crystal/static/fonts/roboto/Roboto-Regular.woff
crystal/static/fonts/roboto/Roboto-Regular.woff2
crystal/static/fonts/roboto/Roboto-Thin.woff
crystal/static/fonts/roboto/Roboto-Thin.woff2
crystal/static/icons/Icon-1024.ico
crystal/static/icons/Icon-1024_saturated.png
crystal/static/icons/crystal_logo_cropped.png
crystal/static/js/plotly-latest.min.js
crystal/templates/crystal_dashboard.html
crystal/templates/js/crystal_dashboard.js
crystal-0.1.0.data/scripts/crystal
crystal-0.1.0.dist-info/METADATA
crystal-0.1.0.dist-info/RECORD
crystal-0.1.0.dist-info/WHEEL
crystal-0.1.0.dist-info/top_level.txt
