Metadata-Version: 2.1
Name: crystal
Version: 0.1.0
Summary: A realtime plotting library built using plot.ly
Home-page: https://github.com/Naresh1318/crystal
Author: Naresh Nagabushan
Author-email: nnaresh@vt.edu
License: MIT
Keywords: plotting charts realtime
Platform: UNKNOWN
Classifier: Development Status :: 3 - Alpha
Classifier: Intended Audience :: Science/Research
Classifier: Programming Language :: Python :: 2.7
Classifier: Programming Language :: Python :: 3.6
Requires-Python: >=3
Requires-Dist: numpy
Requires-Dist: Flask (==1.0.2)
